dtpyapi/__init__.py
dtpyapi/applications/__init__.py
dtpyapi/applications/main.py
dtpyapi/applications/sub.py
dtpyapi/middlewares/__init__.py
dtpyapi/middlewares/http_exception.py
dtpyapi/middlewares/runtime.py
dtpyapi/middlewares/validation_exception.py
dtpyapi/routes/__init__.py
dtpyapi/routes/authentication.py
dtpyapi/routes/response.py
dtpyapi/routes/route.py
dtpyapi/routes/router.py
dtpyapi/schemas/__init__.py
dtpyapi/schemas/enums.py
dtpyapi/schemas/models.py
dtpyapi-1.0.2.dist-info/METADATA
dtpyapi-1.0.2.dist-info/WHEEL
dtpyapi-1.0.2.dist-info/RECORD
