Metadata-Version: 2.3
Name: dtpyapi
Version: 1.0.2
Summary: A package to improved api library to have better development experience.
License: MIT
Author: Reza Shirazi
Author-email: reza@datgate.com
Requires-Python: >=3.11.9,<3.12.0
Classifier: License :: OSI Approved :: MIT License
Classifier: Programming Language :: Python :: 3
Requires-Dist: dtpyutils (>=1.0.0,<1.1.0)
Requires-Dist: fastapi (>=0.115.12,<0.116.0)
Requires-Dist: gunicorn (>=23.0.0,<23.1.0)
Requires-Dist: python-multipart (>=0.0.18,<0.1.0)
Requires-Dist: uvicorn (>=0.34.0,<0.35.0)
